flask_pagerouter/PageRouter.py
flask_pagerouter/__init__.py
flask_pagerouter/pyx_html.py
flask_pagerouter/pyx_template.py
flask_pagerouter-0.1.2.dist-info/METADATA
flask_pagerouter-0.1.2.dist-info/WHEEL
flask_pagerouter-0.1.2.dist-info/top_level.txt
flask_pagerouter-0.1.2.dist-info/RECORD
