Metadata-Version: 2.1
Name: flask-pagerouter
Version: 0.1.2
Summary: A lightweight Python library for page routing in Flask applications.
Author: Etienne DTS
License: MIT
